MANIFEST.in
README
ez_setup.py
libdrizzle.c
setup.py
test.py
test_buffer.py
test_cons.py
drizzle/__init__.py
drizzle/column_types.py
drizzle/db.py
drizzle/errors.py
drizzle/libdrizzle.py
drizzle/librelease.py
python_libdrizzle.egg-info/PKG-INFO
python_libdrizzle.egg-info/SOURCES.txt
python_libdrizzle.egg-info/dependency_links.txt
python_libdrizzle.egg-info/top_level.txt
tests/__init__.py
tests/dbapi20.py
tests/test_drizzle_dbapi20.py