Metadata-Version: 1.0
Name: python-libdrizzle
Version: 0.08.1
Summary: Python wrapper of libdrizzle
Home-page: http://launchpad.net/drizzle-interface
Author: Monty Taylor
Author-email: mordred@inaugust.com
License: BSD
Platform: linux
Classifier: Development Status :: 3 - Alpha
Classifier: Intended Audience :: Developers
Classifier: License :: OSI Approved :: BSD License
Classifier: Operating System :: POSIX :: Linux
Classifier: Operating System :: POSIX :: SunOS/Solaris
Classifier: Operating System :: MacOS :: MacOS X
Classifier: Programming Language :: C
Classifier: Programming Language :: Python
Classifier: Topic :: Database
Classifier: Topic :: Software Development :: Libraries :: Python Modules
